insta_nova/__init__.py
insta_nova/client.py
insta_nova/decorators.py
insta_nova/exceptions.py
insta_nova/validators.py
insta_nova-0.1.1.dist-info/licenses/LICENSE
insta_nova-0.1.1.dist-info/METADATA
insta_nova-0.1.1.dist-info/WHEEL
insta_nova-0.1.1.dist-info/top_level.txt
insta_nova-0.1.1.dist-info/RECORD
