Metadata-Version: 2.4
Name: insta-nova
Version: 0.1.1
Summary: Wrapper for the Instagram Graph API v23.0.
Author-email: Lavanya Mishra <lavanyamishra1996dev@gmail.com>
License: MIT License
Project-URL: Homepage, https://github.com/chessmadridista/insta-nova
Project-URL: Repository, https://github.com/chessmadridista/insta-nova
Project-URL: Issues, https://github.com/chessmadridista/insta-nova/issues
Requires-Python: >=3.7
License-File: LICENSE
Requires-Dist: certifi==2025.7.9
Requires-Dist: charset-normalizer==3.4.2
Requires-Dist: exceptiongroup==1.3.0
Requires-Dist: idna==3.10
Requires-Dist: iniconfig==2.1.0
Requires-Dist: packaging==25.0
Requires-Dist: pluggy==1.6.0
Requires-Dist: Pygments==2.19.2
Requires-Dist: pytest==8.4.1
Requires-Dist: PyYAML==6.0.2
Requires-Dist: requests==2.32.4
Requires-Dist: responses==0.25.7
Requires-Dist: tomli==2.2.1
Requires-Dist: typing_extensions==4.14.1
Requires-Dist: urllib3==2.5.0
Provides-Extra: dev
Requires-Dist: black; extra == "dev"
Requires-Dist: flake8; extra == "dev"
Requires-Dist: mypy; extra == "dev"
Requires-Dist: pytest; extra == "dev"
Dynamic: license-file
